MANIFEST.in
README.txt
setup.py
docs/HISTORY.txt
docs/LICENSE.txt
src/silva/__init__.py
src/silva.fanstatic.egg-info/PKG-INFO
src/silva.fanstatic.egg-info/SOURCES.txt
src/silva.fanstatic.egg-info/dependency_links.txt
src/silva.fanstatic.egg-info/entry_points.txt
src/silva.fanstatic.egg-info/namespace_packages.txt
src/silva.fanstatic.egg-info/not-zip-safe
src/silva.fanstatic.egg-info/requires.txt
src/silva.fanstatic.egg-info/top_level.txt
src/silva/fanstatic/__init__.py
src/silva/fanstatic/configure.zcml
src/silva/fanstatic/extending.py
src/silva/fanstatic/injector.py
src/silva/fanstatic/interfaces.py
src/silva/fanstatic/resources.py
src/silva/fanstatic/support.py
src/silva/fanstatic/martiansupport/__init__.py
src/silva/fanstatic/martiansupport/resources.py
src/silva/fanstatic/tests/__init__.py
src/silva/fanstatic/tests/test_dependencies.py
src/silva/fanstatic/tests/test_resources.py
src/silva/fanstatic/tests/dependencies/__init__.py
src/silva/fanstatic/tests/dependencies/external.txt
src/silva/fanstatic/tests/dependencies/external_fixture.py
src/silva/fanstatic/tests/dependencies/inheritance.txt
src/silva/fanstatic/tests/dependencies/inheritance_fixture.py
src/silva/fanstatic/tests/dependencies/static/base.css
src/silva/fanstatic/tests/dependencies/static/featurea.css
src/silva/fanstatic/tests/dependencies/static/featureb.css
src/silva/fanstatic/tests/dependencies/static/full.css