Metadata-Version: 1.1
Name: silva.fanstatic
Version: 1.2
Summary: Integration of fanstatic in Silva CMS
Home-page: https://github.com/silvacms/silva.fanstatic
Author: Sylvain Viollon
Author-email: info@infrae.com
License: BSD
Keywords: zope2 fanstatic silva
Platform: UNKNOWN
Classifier: Environment :: Web Environment
Classifier: Intended Audience :: Developers
Classifier: License :: OSI Approved :: Zope Public License
Classifier: Programming Language :: Python
Classifier: Topic :: Software Development :: Libraries :: Python Modules
Classifier: Framework :: Zope2
